goocalendar/__init__.py
goocalendar/_calendar.py
goocalendar/_event.py
goocalendar/util.py
GooCalendar-0.8.0.dist-info/LICENSE
GooCalendar-0.8.0.dist-info/METADATA
GooCalendar-0.8.0.dist-info/WHEEL
GooCalendar-0.8.0.dist-info/top_level.txt
GooCalendar-0.8.0.dist-info/RECORD
